pyb2d_jupyterlite_backend/__init__.py
pyb2d_jupyterlite_backend/async_events.py
pyb2d_jupyterlite_backend/async_jupyter_gui.py
pyb2d_jupyterlite_backend/plot.py
pyb2d_jupyterlite_backend-0.4.2.dist-info/LICENSE
pyb2d_jupyterlite_backend-0.4.2.dist-info/METADATA
pyb2d_jupyterlite_backend-0.4.2.dist-info/WHEEL
pyb2d_jupyterlite_backend-0.4.2.dist-info/top_level.txt
pyb2d_jupyterlite_backend-0.4.2.dist-info/RECORD
