Metadata-Version: 2.1
Name: pyb2d-jupyterlite-backend
Version: 0.4.2
Summary: UNKNOWN
License: UNKNOWN
Platform: UNKNOWN
License-File: LICENSE
Requires-Dist: ipycanvas
Requires-Dist: ipyevents
